Metadata-Version: 2.1
Name: python-singleton-metaclasses
Version: 0.2.1
Summary: A package of python metclasses for implementing singleton and related patterns.
Home-page: https://github.com/zcutlip/py-singleton-metaclasses
Author: Zachary Cutlip
Author-email: uid000@gmail.com
License: MIT
Requires-Python: >=3.7
License-File: LICENSE
